命令：javap -p -v -c Sychronized.class

打印输出：
lassfile /C:/Users/steve/IdeaProjects/Restart_Study/target/classes/Java_Basic/sychronize/Sychronized.class
  Last modified 2020-6-1; size 745 bytes
  MD5 checksum 82acb7b2948c3b6bc3a3d4b42a91fdcf
  Compiled from "Sychronized.java"
public class Java_Basic.sychronize.Sychronized
  minor version: 0
  major version: 52
  flags: ACC_PUBLIC, ACC_SUPER
Constant pool:
   #1 = Methodref          #5.#22         // java/lang/Object."<init>":()V
   #2 = Class              #23            // Java_Basic/sychronize/Sychronized
   #3 = Class              #24            // Java_Basic/serialize/Student
   #4 = Methodref          #3.#22         // Java_Basic/serialize/Student."<init>":()V
   #5 = Class              #25            // java/lang/Object
   #6 = Utf8               <init>
   #7 = Utf8               ()V
   #8 = Utf8               Code
   #9 = Utf8               LineNumberTable
  #10 = Utf8               LocalVariableTable
  #11 = Utf8               this
  #12 = Utf8               LJava_Basic/sychronize/Sychronized;
  #13 = Utf8               husbandFunction
  #14 = Utf8               husbandClass
  #15 = Utf8               StackMapTable
  #16 = Class              #23            // Java_Basic/sychronize/Sychronized
  #17 = Class              #25            // java/lang/Object
  #18 = Class              #26            // java/lang/Throwable
  #19 = Utf8               husbandObject
  #20 = Utf8               SourceFile
  #21 = Utf8               Sychronized.java
  #22 = NameAndType        #6:#7          // "<init>":()V
  #23 = Utf8               Java_Basic/sychronize/Sychronized
  #24 = Utf8               Java_Basic/serialize/Student
  #25 = Utf8               java/lang/Object
  #26 = Utf8               java/lang/Throwable
{
  public Java_Basic.sychronize.Sychronized();
    descriptor: ()V
    flags: ACC_PUBLIC
    Code:
      stack=1, locals=1, args_size=1
         0: aload_0
         1: invokespecial #1                  // Method java/lang/Object."<init>":()V
         4: return
      LineNumberTable:
        line 12: 0
      LocalVariableTable:
        Start  Length  Slot  Name   Signature
            0       5     0  this   LJava_Basic/sychronize/Sychronized;

  public synchronized void husbandFunction();
    descriptor: ()V
    flags: ACC_PUBLIC, ACC_SYNCHRONIZED
    Code:
      stack=0, locals=1, args_size=1
         0: return
      LineNumberTable:
        line 20: 0
      LocalVariableTable:
        Start  Length  Slot  Name   Signature
            0       1     0  this   LJava_Basic/sychronize/Sychronized;

  public void husbandClass();
    descriptor: ()V
    flags: ACC_PUBLIC
    Code:
      stack=2, locals=3, args_size=1
         0: ldc           #2                  // class Java_Basic/sychronize/Sychronized
         2: dup
         3: astore_1
         4: monitorenter
         5: aload_1
         6: monitorexit
         7: goto          15
        10: astore_2
        11: aload_1
        12: monitorexit
        13: aload_2
        14: athrow
        15: return
      Exception table:
         from    to  target type
             5     7    10   any
            10    13    10   any
      LineNumberTable:
        line 30: 0
        line 32: 5
        line 33: 15
      LocalVariableTable:
        Start  Length  Slot  Name   Signature
            0      16     0  this   LJava_Basic/sychronize/Sychronized;
      StackMapTable: number_of_entries = 2
        frame_type = 255 /* full_frame */
          offset_delta = 10
          locals = [ class Java_Basic/sychronize/Sychronized, class java/lang/Object ]
          stack = [ class java/lang/Throwable ]
        frame_type = 250 /* chop */
          offset_delta = 4

  public void husbandObject();
    descriptor: ()V
    flags: ACC_PUBLIC
    Code:
      stack=2, locals=3, args_size=1
         0: new           #3                  // class Java_Basic/serialize/Student
         3: dup
         4: invokespecial #4                  // Method Java_Basic/serialize/Student."<init>":()V
         7: dup
         8: astore_1
         9: monitorenter
        10: aload_1
        11: monitorexit
        12: goto          20
        15: astore_2
        16: aload_1
        17: monitorexit
        18: aload_2
        19: athrow
        20: return
      Exception table:
         from    to  target type
            10    12    15   any
            15    18    15   any
      LineNumberTable:
        line 42: 0
        line 44: 10
        line 45: 20
      LocalVariableTable:
        Start  Length  Slot  Name   Signature
            0      21     0  this   LJava_Basic/sychronize/Sychronized;
      StackMapTable: number_of_entries = 2
        frame_type = 255 /* full_frame */
          offset_delta = 15
          locals = [ class Java_Basic/sychronize/Sychronized, class java/lang/Object ]
          stack = [ class java/lang/Throwable ]
        frame_type = 250 /* chop */
          offset_delta = 4
}
SourceFile: "Sychronized.java"
